COPYING
MANIFEST.in
README.rst
bootstrap-buildout.py
buildout.cfg
evaluate_scores.sh
plot_combined_det.sh
preprocess_scores.sh
requirements.txt
setup.py
version.txt
bob/__init__.py
bob.paper.btas_c2016.egg-info/PKG-INFO
bob.paper.btas_c2016.egg-info/SOURCES.txt
bob.paper.btas_c2016.egg-info/dependency_links.txt
bob.paper.btas_c2016.egg-info/entry_points.txt
bob.paper.btas_c2016.egg-info/requires.txt
bob.paper.btas_c2016.egg-info/top_level.txt
bob/paper/__init__.py
bob/paper/btas_c2016/__init__.py
bob/paper/btas_c2016/baseline.py
bob/paper/btas_c2016/baseline_test.py
bob/paper/btas_c2016/parse_random_test_list.py
bob/paper/btas_c2016/plot_det_from_sets.py
bob/paper/btas_c2016/plot_far_frr_pad.py
bob/paper/btas_c2016/plot_pad_results.py
bob/paper/btas_c2016/split_dev_scores.py
bob/paper/btas_c2016/test_scores_derandomize.py
doc/conf.py
doc/index.rst
submissions/Baseline/dev-scores.txt
submissions/Baseline/test-scores_v1.txt
submissions/Baseline/test-scores_v2.txt
submissions/CPqD/dev-scores.txt
submissions/CPqD/test-scores_v1.txt
submissions/CPqD/test-scores_v2.txt
submissions/IITKGP_ABSP/dev-scores.txt
submissions/IITKGP_ABSP/test-scores_v1.txt
submissions/IITKGP_ABSP/test-scores_v2.txt
submissions/Idiap/dev-scores.txt
submissions/Idiap/test-scores_v1.txt
submissions/Idiap/test-scores_v2.txt
submissions/SJTUSpeech/dev-scores.txt
submissions/SJTUSpeech/test-scores_v1.txt
submissions/SJTUSpeech/test-scores_v2.txt
submissions/to_recover_test_files/attack-btas2016-allsupports-test.txt
submissions/to_recover_test_files/attack-dev-anchors4test.txt
submissions/to_recover_test_files/btas2016-testset-match-names.txt
submissions/to_recover_test_files/real-btas2016-allsupports-test.txt
submissions/to_recover_test_files/real-dev-anchors4test.txt
submissions/to_recover_test_files/test-list.txt