Metadata-Version: 1.1
Name: bob.paper.btas-c2016
Version: 1.0.3
Summary: Package for BTAS Speaker Anti-spoofing Competition
Home-page: https://gitlab.idiap.ch/bob/bob.paper.btas_c2016
Author: Pavel Korshunov
Author-email: pavel.korshunov@idiap.ch
License: GPLv3
Keywords: Bob package,BTAS competition,speaker anti-spoofing
Platform: UNKNOWN
Classifier: Framework :: Bob
Classifier: Development Status :: 3 - Alpha
Classifier: Intended Audience :: Developers
Classifier: License :: OSI Approved :: GNU General Public License v3 (GPLv3)
Classifier: Natural Language :: English
Classifier: Programming Language :: Python
Classifier: Topic :: Scientific/Engineering :: Artificial Intelligence
